mathdunders/__init__.py
mathdunders/mathdunders.py
mathdunders/test_mathdunders.py
mathdunders-0.4.2.dist-info/LICENSE.txt
mathdunders-0.4.2.dist-info/METADATA
mathdunders-0.4.2.dist-info/WHEEL
mathdunders-0.4.2.dist-info/top_level.txt
mathdunders-0.4.2.dist-info/RECORD
