Metadata-Version: 2.1
Name: mathdunders
Version: 0.4.2
Summary: Decorator that automatically adds math dunders to a class.
Home-page: https://github.com/discretegames/mathdunders
Author: discretegames
Author-email: discretizedgames@gmail.com
License: MIT
Keywords: python,math,mathematics,dunder,double under,underscore,magic method,number
Platform: UNKNOWN
Classifier: Development Status :: 5 - Production/Stable
Classifier: Intended Audience :: Developers
Classifier: Topic :: Scientific/Engineering :: Mathematics
Classifier: Topic :: Utilities
Classifier: License :: OSI Approved :: MIT License
Classifier: Programming Language :: Python :: 3
